collective.searchandreplace-8.3.1-py3.12-nspkg.pth
collective/searchandreplace/__init__.py
collective/searchandreplace/configure.zcml
collective/searchandreplace/interfaces.py
collective/searchandreplace/searchreplaceutility.py
collective/searchandreplace/testing.py
collective/searchandreplace/testing.zcml
collective/searchandreplace/tool.gif
collective/searchandreplace/update_locales.sh
collective/searchandreplace/upgrade.py
collective/searchandreplace/version.txt
collective/searchandreplace/browser/__init__.py
collective/searchandreplace/browser/configure.zcml
collective/searchandreplace/browser/controlpanel.py
collective/searchandreplace/browser/searchreplaceform.py
collective/searchandreplace/browser/searchreplacetable.pt
collective/searchandreplace/browser/searchreplacetable.py
collective/searchandreplace/browser/resources/edit_inline.png
collective/searchandreplace/locales/SearchAndReplace.pot
collective/searchandreplace/locales/af/LC_MESSAGES/SearchAndReplace.po
collective/searchandreplace/locales/ar/LC_MESSAGES/SearchAndReplace.po
collective/searchandreplace/locales/bn/LC_MESSAGES/SearchAndReplace.po
collective/searchandreplace/locales/ca/LC_MESSAGES/SearchAndReplace.po
collective/searchandreplace/locales/de/LC_MESSAGES/SearchAndReplace.po
collective/searchandreplace/locales/en/LC_MESSAGES/SearchAndReplace.po
collective/searchandreplace/locales/es/LC_MESSAGES/SearchAndReplace.po
collective/searchandreplace/locales/fr/LC_MESSAGES/SearchAndReplace.po
collective/searchandreplace/locales/hi/LC_MESSAGES/SearchAndReplace.po
collective/searchandreplace/locales/hu/LC_MESSAGES/SearchAndReplace.po
collective/searchandreplace/locales/it/LC_MESSAGES/SearchAndReplace.po
collective/searchandreplace/locales/ja/LC_MESSAGES/SearchAndReplace.po
collective/searchandreplace/locales/ko/LC_MESSAGES/SearchAndReplace.po
collective/searchandreplace/locales/ne/LC_MESSAGES/SearchAndReplace.po
collective/searchandreplace/locales/nl/LC_MESSAGES/SearchAndReplace.po
collective.searchandreplace-8.3.1.dist-info/METADATA
collective.searchandreplace-8.3.1.dist-info/WHEEL
collective.searchandreplace-8.3.1.dist-info/entry_points.txt
collective.searchandreplace-8.3.1.dist-info/namespace_packages.txt
collective.searchandreplace-8.3.1.dist-info/top_level.txt
collective.searchandreplace-8.3.1.dist-info/RECORD
