Metadata-Version: 2.1
Name: collective.searchandreplace
Version: 8.3.1
Summary: Batch Search and Replace
Home-page: https://github.com/collective/collective.searchandreplace
Author: enPraxis
Author-email: info@enpraxis.net
Maintainer: Maurits van Rees
Maintainer-email: m.van.rees@zestsoftware.nl
License: GPL
Keywords: batch search replace
Classifier: Development Status :: 5 - Production/Stable
Classifier: Framework :: Plone
Classifier: Framework :: Plone :: 4.3
Classifier: Framework :: Plone :: 5.1
Classifier: Framework :: Plone :: 5.2
Classifier: Framework :: Plone :: 6.0
Classifier: License :: OSI Approved :: GNU General Public License (GPL)
Classifier: Programming Language :: Python
Classifier: Programming Language :: Python :: 2.7
Classifier: Programming Language :: Python :: 3.7
Classifier: Programming Language :: Python :: 3.8
Classifier: Programming Language :: Python :: 3.9
Classifier: Programming Language :: Python :: 3.10
Classifier: Programming Language :: Python :: 3.11
Classifier: Topic :: Software Development :: Libraries :: Python Modules
Requires-Python: >=2.7,!=3.0.*,!=3.1.*,!=3.2.*,!=3.3.*,!=3.4.*,!=3.5.*
Requires-Dist: Acquisition
Requires-Dist: plone.api
Requires-Dist: plone.app.layout
Requires-Dist: plone.app.textfield
Requires-Dist: plone.autoform
Requires-Dist: plone.resource
Requires-Dist: Products.CMFCore
Requires-Dist: Products.CMFPlone
Requires-Dist: Products.statusmessages
Requires-Dist: setuptools
Requires-Dist: Zope2
Requires-Dist: z3c.form
Requires-Dist: zope.component
Requires-Dist: zope.contentprovider
Requires-Dist: zope.i18nmessageid
Requires-Dist: zope.interface
Requires-Dist: zope.publisher
Requires-Dist: zope.schema
Provides-Extra: test
Requires-Dist: collective.dexteritytextindexer; extra == "test"
Requires-Dist: plone.app.testing; extra == "test"
Provides-Extra: pytest
Requires-Dist: pytest; extra == "pytest"
Requires-Dist: requests; extra == "pytest"
Requires-Dist: zope.pytestlayer; extra == "pytest"
